webauto_hj3415/__init__.py
webauto_hj3415/cli.py
webauto_hj3415/ecolian_captcha.png
webauto_hj3415/codes/__init__.py
webauto_hj3415/codes/dentaljob.py
webauto_hj3415/codes/ecolian.py
webauto_hj3415/codes/ecolian_old.py
webauto_hj3415/codes/sono.py
webauto_hj3415-0.1.2.dist-info/METADATA
webauto_hj3415-0.1.2.dist-info/WHEEL
webauto_hj3415-0.1.2.dist-info/entry_points.txt
webauto_hj3415-0.1.2.dist-info/licenses/LICENSE
webauto_hj3415-0.1.2.dist-info/RECORD
